{
  "assets": [
    {
      "id": "el-13-_JY5",
      "layers": [
        {
          "ddd": 0,
          "ind": 1,
          "ty": 4,
          "nm": "Layer 1",
          "hd": false,
          "sr": 1,
          "ks": {
            "a": {
              "a": 0,
              "k": [
                85.176,
                82.396
              ]
            },
            "o": {
              "a": 0,
              "k": 100
            },
            "p": {
              "a": 0,
              "k": [
                108.21,
                105.384
              ]
            },
            "r": {
              "a": 0,
              "k": 0
            },
            "s": {
              "a": 0,
              "k": [
                100,
                100
              ]
            },
            "sk": {
              "a": 0,
              "k": 0
            },
            "sa": {
              "a": 0,
              "k": 0
            }
          },
          "ao": 0,
          "ip": 0,
          "op": 28,
          "st": 0,
          "bm": 0,
          "shapes": [
            {
              "ty": "gr",
              "hd": false,
              "nm": "Path 1 Group",
              "bm": 0,
              "it": [
                {
                  "ty": "sh",
                  "hd": false,
                  "nm": "Path 1",
                  "d": 1,
                  "ks": {
                    "a": 0,
                    "k": {
                      "c": false,
                      "i": [
                        [
                          0,
                          0
                        ],
                        [
                          0.733,
                          -1.383
                        ],
                        [
                          0,
                          -1.357
                        ],
                        [
                          -0.383,
                          -0.75
                        ],
                        [
                          -4.229,
                          -4.245
                        ],
                        [
                          0,
                          -0.096
                        ],
                        [
                          3.239,
                          -3.257
                        ],
                        [
                          0.239,
                          -0.463
                        ],
                        [
                          0,
                          -1.373
                        ],
                        [
                          -0.383,
                          -0.719
                        ],
                        [
                          -0.974,
                          -0.511
                        ],
                        [
                          -1.373,
                          0
                        ],
                        [
                          -0.625,
                          0.335
                        ],
                        [
                          -3.814,
                          3.814
                        ],
                        [
                          -0.096,
                          0
                        ],
                        [
                          -3.223,
                          -3.209
                        ],
                        [
                          -0.589,
                          -0.319
                        ],
                        [
                          -1.421,
                          0
                        ],
                        [
                          -1.181,
                          1.166
                        ],
                        [
                          0,
                          1.724
                        ],
                        [
                          6.733,
                          6.749
                        ],
                        [
                          0,
                          0.128
                        ],
                        [
                          -3.239,
                          3.255
                        ],
                        [
                          -0.018,
                          2.363
                        ],
                        [
                          0.399,
                          0.732
                        ],
                        [
                          1.013,
                          0.532
                        ],
                        [
                          1.293,
                          0
                        ],
                        [
                          6.751,
                          -6.719
                        ],
                        [
                          0.128,
                          0
                        ],
                        [
                          3.207,
                          3.191
                        ],
                        [
                          1.93,
                          0.126
                        ],
                        [
                          0.545,
                          -0.077
                        ]
                      ],
                      "o": [
                        [
                          -1.52,
                          0.373
                        ],
                        [
                          -0.319,
                          0.591
                        ],
                        [
                          0,
                          1.437
                        ],
                        [
                          0.319,
                          0.589
                        ],
                        [
                          3.207,
                          3.223
                        ],
                        [
                          0,
                          0.096
                        ],
                        [
                          -3.816,
                          3.812
                        ],
                        [
                          -0.335,
                          0.623
                        ],
                        [
                          0,
                          1.417
                        ],
                        [
                          0.511,
                          0.958
                        ],
                        [
                          0.621,
                          0.335
                        ],
                        [
                          1.373,
                          0
                        ],
                        [
                          0.461,
                          -0.24
                        ],
                        [
                          3.253,
                          -3.239
                        ],
                        [
                          0.096,
                          0
                        ],
                        [
                          4.231,
                          4.211
                        ],
                        [
                          0.734,
                          0.383
                        ],
                        [
                          1.852,
                          0
                        ],
                        [
                          1.054,
                          -1.068
                        ],
                        [
                          0.016,
                          -2.297
                        ],
                        [
                          -3.193,
                          -3.209
                        ],
                        [
                          0,
                          -0.128
                        ],
                        [
                          6.719,
                          -6.749
                        ],
                        [
                          0,
                          -1.277
                        ],
                        [
                          -0.526,
                          -1.016
                        ],
                        [
                          -0.764,
                          -0.413
                        ],
                        [
                          -2.361,
                          0.014
                        ],
                        [
                          -3.253,
                          3.239
                        ],
                        [
                          -0.128,
                          0
                        ],
                        [
                          -6.432,
                          -6.416
                        ],
                        [
                          -0.548,
                          -0.046
                        ],
                        [
                          0,
                          0
                        ]
                      ],
                      "v": [
                        [
                          37.339,
                          130.197
                        ],
                        [
                          33.797,
                          132.957
                        ],
                        [
                          33.43,
                          135.238
                        ],
                        [
                          33.861,
                          137.664
                        ],
                        [
                          40.133,
                          144.334
                        ],
                        [
                          45.957,
                          150.365
                        ],
                        [
                          40.069,
                          156.462
                        ],
                        [
                          33.813,
                          163.083
                        ],
                        [
                          33.43,
                          165.398
                        ],
                        [
                          33.861,
                          167.791
                        ],
                        [
                          36.224,
                          170.12
                        ],
                        [
                          38.537,
                          170.503
                        ],
                        [
                          40.852,
                          170.12
                        ],
                        [
                          47.473,
                          163.866
                        ],
                        [
                          53.568,
                          157.978
                        ],
                        [
                          59.599,
                          163.802
                        ],
                        [
                          66.285,
                          170.072
                        ],
                        [
                          68.696,
                          170.503
                        ],
                        [
                          72.366,
                          169.082
                        ],
                        [
                          73.771,
                          165.396
                        ],
                        [
                          67.085,
                          156.382
                        ],
                        [
                          61.276,
                          150.317
                        ],
                        [
                          67.163,
                          144.174
                        ],
                        [
                          73.786,
                          135.238
                        ],
                        [
                          73.34,
                          132.988
                        ],
                        [
                          70.977,
                          130.61
                        ],
                        [
                          68.696,
                          130.149
                        ],
                        [
                          59.759,
                          136.77
                        ],
                        [
                          53.616,
                          142.658
                        ],
                        [
                          47.553,
                          136.85
                        ],
                        [
                          38.984,
                          130.149
                        ],
                        [
                          37.339,
                          130.195
                        ]
                      ]
                    }
                  }
                },
                {
                  "ty": "fl",
                  "hd": false,
                  "bm": 0,
                  "c": {
                    "a": 0,
                    "k": [
                      0,
                      0.718,
                      0.8
                    ]
                  },
                  "r": 1,
                  "o": {
                    "a": 0,
                    "k": 100
                  }
                },
                {
                  "ty": "tr",
                  "nm": "Transform",
                  "a": {
                    "a": 0,
                    "k": [
                      53.608,
                      150.313
                    ]
                  },
                  "o": {
                    "a": 0,
                    "k": 100
                  },
                  "p": {
                    "a": 0,
                    "k": [
                      53.608,
                      150.313
                    ]
                  },
                  "r": {
                    "a": 1,
                    "k": [
                      {
                        "t": 0,
                        "s": [
                          0
                        ],
                        "i": {
                          "x": 0.75,
                          "y": 0.75
                        },
                        "o": {
                          "x": 0.25,
                          "y": 0.25
                        }
                      },
                      {
                        "t": 12,
                        "s": [
                          0
                        ],
                        "i": {
                          "x": 0.75,
                          "y": 0.75
                        },
                        "o": {
                          "x": 0.25,
                          "y": 0.25
                        }
                      },
                      {
                        "t": 18,
                        "s": [
                          180
                        ],
                        "i": {
                          "x": 0,
                          "y": 0
                        },
                        "o": {
                          "x": 1,
                          "y": 1
                        }
                      }
                    ]
                  },
                  "s": {
                    "a": 0,
                    "k": [
                      100,
                      100
                    ]
                  },
                  "sk": {
                    "a": 0,
                    "k": 0
                  },
                  "sa": {
                    "a": 0,
                    "k": 0
                  }
                }
              ],
              "np": 0
            },
            {
              "ty": "gr",
              "hd": false,
              "nm": "Path 1 Group",
              "bm": 0,
              "it": [
                {
                  "ty": "sh",
                  "hd": false,
                  "nm": "Path 1",
                  "d": 1,
                  "ks": {
                    "a": 0,
                    "k": {
                      "c": false,
                      "i": [
                        [
                          0,
                          0
                        ],
                        [
                          0.635,
                          -1.152
                        ],
                        [
                          0,
                          -1.421
                        ],
                        [
                          -0.431,
                          -0.764
                        ],
                        [
                          -1.054,
                          -0.367
                        ],
                        [
                          -21.192,
                          0
                        ],
                        [
                          0,
                          0
                        ],
                        [
                          0,
                          0
                        ],
                        [
                          -0.463,
                          0.91
                        ],
                        [
                          2.906,
                          1.102
                        ],
                        [
                          0,
                          0
                        ],
                        [
                          0,
                          0
                        ],
                        [
                          0.639,
                          -0.208
                        ]
                      ],
                      "o": [
                        [
                          -1.231,
                          0.465
                        ],
                        [
                          -0.509,
                          0.926
                        ],
                        [
                          0,
                          1.387
                        ],
                        [
                          0.605,
                          1.118
                        ],
                        [
                          0.782,
                          0.271
                        ],
                        [
                          0,
                          0
                        ],
                        [
                          0,
                          0
                        ],
                        [
                          1.004,
                          -0.399
                        ],
                        [
                          1.421,
                          -2.794
                        ],
                        [
                          0,
                          0
                        ],
                        [
                          0,
                          0
                        ],
                        [
                          -19.723,
                          0.016
                        ],
                        [
                          0,
                          0
                        ]
                      ],
                      "v": [
                        [
                          127.339,
                          48.607
                        ],
                        [
                          124.449,
                          51.112
                        ],
                        [
                          123.908,
                          53.618
                        ],
                        [
                          124.387,
                          55.979
                        ],
                        [
                          127.227,
                          58.516
                        ],
                        [
                          150.397,
                          58.803
                        ],
                        [
                          172.737,
                          58.803
                        ],
                        [
                          173.631,
                          58.436
                        ],
                        [
                          176.311,
                          56.059
                        ],
                        [
                          173.517,
                          48.703
                        ],
                        [
                          172.625,
                          48.351
                        ],
                        [
                          150.349,
                          48.351
                        ],
                        [
                          127.339,
                          48.607
                        ]
                      ]
                    }
                  }
                },
                {
                  "ty": "fl",
                  "hd": false,
                  "bm": 0,
                  "c": {
                    "a": 0,
                    "k": [
                      0,
                      0.718,
                      0.8
                    ]
                  },
                  "r": 1,
                  "o": {
                    "a": 0,
                    "k": 100
                  }
                },
                {
                  "ty": "tr",
                  "nm": "Transform",
                  "a": {
                    "a": 0,
                    "k": [
                      150.398,
                      53.577
                    ]
                  },
                  "o": {
                    "a": 0,
                    "k": 100
                  },
                  "p": {
                    "a": 0,
                    "k": [
                      150.398,
                      53.577
                    ]
                  },
                  "r": {
                    "a": 1,
                    "k": [
                      {
                        "t": 0,
                        "s": [
                          0
                        ],
                        "i": {
                          "x": 0.75,
                          "y": 0.75
                        },
                        "o": {
                          "x": 0.25,
                          "y": 0.25
                        }
                      },
                      {
                        "t": 6,
                        "s": [
                          0
                        ],
                        "i": {
                          "x": 0.75,
                          "y": 0.75
                        },
                        "o": {
                          "x": 0.25,
                          "y": 0.25
                        }
                      },
                      {
                        "t": 12,
                        "s": [
                          180
                        ],
                        "i": {
                          "x": 0,
                          "y": 0
                        },
                        "o": {
                          "x": 1,
                          "y": 1
                        }
                      }
                    ]
                  },
                  "s": {
                    "a": 0,
                    "k": [
                      100,
                      100
                    ]
                  },
                  "sk": {
                    "a": 0,
                    "k": 0
                  },
                  "sa": {
                    "a": 0,
                    "k": 0
                  }
                }
              ],
              "np": 0
            },
            {
              "ty": "gr",
              "hd": true,
              "nm": "Path 1 Group",
              "bm": 0,
              "it": [
                {
                  "ty": "sh",
                  "hd": true,
                  "nm": "Path 1",
                  "d": 1,
                  "ks": {
                    "a": 0,
                    "k": {
                      "c": false,
                      "i": [
                        [
                          0,
                          0
                        ],
                        [
                          -1.435,
                          -2.76
                        ],
                        [
                          -1.07,
                          -0.303
                        ],
                        [
                          -18.384,
                          0
                        ],
                        [
                          0,
                          0
                        ],
                        [
                          0,
                          0
                        ],
                        [
                          -0.495,
                          1.088
                        ],
                        [
                          0.607,
                          1.277
                        ],
                        [
                          1.179,
                          0.429
                        ],
                        [
                          22.1,
                          0
                        ],
                        [
                          0.814,
                          -0.303
                        ]
                      ],
                      "o": [
                        [
                          -2.874,
                          1.02
                        ],
                        [
                          0.559,
                          1.07
                        ],
                        [
                          0.621,
                          0.191
                        ],
                        [
                          0,
                          0
                        ],
                        [
                          0,
                          0
                        ],
                        [
                          1.197,
                          -0.591
                        ],
                        [
                          0.591,
                          -1.291
                        ],
                        [
                          -0.543,
                          -1.134
                        ],
                        [
                          -0.862,
                          -0.335
                        ],
                        [
                          -21.527,
                          0.016
                        ],
                        [
                          0,
                          0
                        ]
                      ],
                      "v": [
                        [
                          127.53,
                          155.903
                        ],
                        [
                          124.752,
                          163.243
                        ],
                        [
                          127.786,
                          165.812
                        ],
                        [
                          150.876,
                          166.035
                        ],
                        [
                          173.216,
                          166.035
                        ],
                        [
                          174.11,
                          165.604
                        ],
                        [
                          176.758,
                          162.97
                        ],
                        [
                          176.742,
                          158.583
                        ],
                        [
                          173.838,
                          155.919
                        ],
                        [
                          150.668,
                          155.584
                        ],
                        [
                          127.53,
                          155.903
                        ]
                      ]
                    }
                  }
                },
                {
                  "ty": "fl",
                  "hd": false,
                  "bm": 0,
                  "c": {
                    "a": 0,
                    "k": [
                      0,
                      0.718,
                      0.8
                    ]
                  },
                  "r": 1,
                  "o": {
                    "a": 0,
                    "k": 100
                  }
                },
                {
                  "ty": "tr",
                  "nm": "Transform",
                  "a": {
                    "a": 1,
                    "k": [
                      {
                        "t": 0,
                        "s": [
                          124.172,
                          160.809
                        ],
                        "i": {
                          "x": 0.75,
                          "y": 0.75
                        },
                        "o": {
                          "x": 0.25,
                          "y": 0.25
                        }
                      },
                      {
                        "t": 18,
                        "s": [
                          46.717,
                          60.501
                        ],
                        "i": {
                          "x": 0,
                          "y": 0
                        },
                        "o": {
                          "x": 1,
                          "y": 1
                        }
                      }
                    ]
                  },
                  "o": {
                    "a": 0,
                    "k": 100
                  },
                  "p": {
                    "a": 1,
                    "k": [
                      {
                        "t": 0,
                        "s": [
                          124.172,
                          160.809
                        ],
                        "i": {
                          "x": 0.75,
                          "y": 0.75
                        },
                        "o": {
                          "x": 0.25,
                          "y": 0.25
                        },
                        "ti": [
                          0,
                          0
                        ],
                        "to": [
                          0,
                          0
                        ]
                      },
                      {
                        "t": 18,
                        "s": [
                          46.717,
                          60.501
                        ],
                        "i": {
                          "x": 0,
                          "y": 0
                        },
                        "o": {
                          "x": 1,
                          "y": 1
                        }
                      }
                    ]
                  },
                  "r": {
                    "a": 0,
                    "k": 0
                  },
                  "s": {
                    "a": 1,
                    "k": [
                      {
                        "t": 0,
                        "s": [
                          100,
                          100
                        ],
                        "i": {
                          "x": 0.75,
                          "y": 0.75
                        },
                        "o": {
                          "x": 0.25,
                          "y": 0.25
                        }
                      },
                      {
                        "t": 18,
                        "s": [
                          100,
                          100
                        ],
                        "i": {
                          "x": 0.75,
                          "y": 0.75
                        },
                        "o": {
                          "x": 0.25,
                          "y": 0.25
                        }
                      },
                      {
                        "t": 22.5,
                        "s": [
                          0,
                          100
                        ],
                        "i": {
                          "x": 0.75,
                          "y": 0.75
                        },
                        "o": {
                          "x": 0.25,
                          "y": 0.25
                        }
                      },
                      {
                        "t": 27,
                        "s": [
                          100,
                          100
                        ],
                        "i": {
                          "x": 0,
                          "y": 0
                        },
                        "o": {
                          "x": 1,
                          "y": 1
                        }
                      }
                    ]
                  },
                  "sk": {
                    "a": 0,
                    "k": 0
                  },
                  "sa": {
                    "a": 0,
                    "k": 0
                  }
                }
              ],
              "np": 0
            },
            {
              "ty": "gr",
              "hd": false,
              "nm": "Path 1 Group",
              "bm": 0,
              "it": [
                {
                  "ty": "sh",
                  "hd": false,
                  "nm": "Path 1",
                  "d": 1,
                  "ks": {
                    "a": 0,
                    "k": {
                      "c": false,
                      "i": [
                        [
                          0,
                          0
                        ],
                        [
                          0,
                          -2.361
                        ],
                        [
                          -1.964,
                          -0.942
                        ],
                        [
                          0,
                          0
                        ],
                        [
                          0,
                          0
                        ],
                        [
                          0,
                          0
                        ],
                        [
                          3.94,
                          1.996
                        ],
                        [
                          0,
                          0
                        ],
                        [
                          0,
                          0
                        ],
                        [
                          0.575,
                          -0.16
                        ]
                      ],
                      "o": [
                        [
                          -2.123,
                          0.575
                        ],
                        [
                          0,
                          2.026
                        ],
                        [
                          0,
                          0
                        ],
                        [
                          0,
                          0
                        ],
                        [
                          0,
                          0
                        ],
                        [
                          4.037,
                          -2.012
                        ],
                        [
                          0,
                          0
                        ],
                        [
                          0,
                          0
                        ],
                        [
                          -17.522,
                          -0.016
                        ],
                        [
                          0,
                          0
                        ]
                      ],
                      "v": [
                        [
                          127.163,
                          134.902
                        ],
                        [
                          123.509,
                          139.961
                        ],
                        [
                          126.7,
                          144.781
                        ],
                        [
                          127.419,
                          145.13
                        ],
                        [
                          172.577,
                          145.13
                        ],
                        [
                          173.471,
                          144.685
                        ],
                        [
                          173.678,
                          135.238
                        ],
                        [
                          172.736,
                          134.759
                        ],
                        [
                          150.317,
                          134.727
                        ],
                        [
                          127.163,
                          134.902
                        ]
                      ]
                    }
                  }
                },
                {
                  "ty": "fl",
                  "hd": false,
                  "bm": 0,
                  "c": {
                    "a": 0,
                    "k": [
                      0,
                      0.718,
                      0.8
                    ]
                  },
                  "r": 1,
                  "o": {
                    "a": 0,
                    "k": 100
                  }
                },
                {
                  "ty": "tr",
                  "nm": "Transform",
                  "a": {
                    "a": 0,
                    "k": [
                      123.509,
                      139.927
                    ]
                  },
                  "o": {
                    "a": 0,
                    "k": 100
                  },
                  "p": {
                    "a": 0,
                    "k": [
                      122.967,
                      159.216
                    ]
                  },
                  "r": {
                    "a": 0,
                    "k": 0
                  },
                  "s": {
                    "a": 1,
                    "k": [
                      {
                        "t": 0,
                        "s": [
                          100,
                          100
                        ],
                        "i": {
                          "x": 0.75,
                          "y": 0.75
                        },
                        "o": {
                          "x": 0.25,
                          "y": 0.25
                        }
                      },
                      {
                        "t": 18,
                        "s": [
                          100,
                          100
                        ],
                        "i": {
                          "x": 0.75,
                          "y": 0.75
                        },
                        "o": {
                          "x": 0.25,
                          "y": 0.25
                        }
                      },
                      {
                        "t": 22.5,
                        "s": [
                          0,
                          100
                        ],
                        "i": {
                          "x": 0.75,
                          "y": 0.75
                        },
                        "o": {
                          "x": 0.25,
                          "y": 0.25
                        }
                      },
                      {
                        "t": 27,
                        "s": [
                          100,
                          100
                        ],
                        "i": {
                          "x": 0,
                          "y": 0
                        },
                        "o": {
                          "x": 1,
                          "y": 1
                        }
                      }
                    ]
                  },
                  "sk": {
                    "a": 0,
                    "k": 0
                  },
                  "sa": {
                    "a": 0,
                    "k": 0
                  }
                }
              ],
              "np": 0
            },
            {
              "ty": "gr",
              "hd": false,
              "nm": "Path 1 Group",
              "bm": 0,
              "it": [
                {
                  "ty": "sh",
                  "hd": false,
                  "nm": "Path 1",
                  "d": 1,
                  "ks": {
                    "a": 0,
                    "k": {
                      "c": false,
                      "i": [
                        [
                          0,
                          0
                        ],
                        [
                          0,
                          -2.361
                        ],
                        [
                          -1.964,
                          -0.942
                        ],
                        [
                          0,
                          0
                        ],
                        [
                          0,
                          0
                        ],
                        [
                          0,
                          0
                        ],
                        [
                          3.94,
                          1.996
                        ],
                        [
                          0,
                          0
                        ],
                        [
                          0,
                          0
                        ],
                        [
                          0.575,
                          -0.16
                        ]
                      ],
                      "o": [
                        [
                          -2.123,
                          0.575
                        ],
                        [
                          0,
                          2.026
                        ],
                        [
                          0,
                          0
                        ],
                        [
                          0,
                          0
                        ],
                        [
                          0,
                          0
                        ],
                        [
                          4.037,
                          -2.012
                        ],
                        [
                          0,
                          0
                        ],
                        [
                          0,
                          0
                        ],
                        [
                          -17.522,
                          -0.016
                        ],
                        [
                          0,
                          0
                        ]
                      ],
                      "v": [
                        [
                          127.163,
                          134.902
                        ],
                        [
                          123.509,
                          139.961
                        ],
                        [
                          126.7,
                          144.781
                        ],
                        [
                          127.419,
                          145.13
                        ],
                        [
                          172.577,
                          145.13
                        ],
                        [
                          173.471,
                          144.685
                        ],
                        [
                          173.678,
                          135.238
                        ],
                        [
                          172.736,
                          134.759
                        ],
                        [
                          150.317,
                          134.727
                        ],
                        [
                          127.163,
                          134.902
                        ]
                      ]
                    }
                  }
                },
                {
                  "ty": "fl",
                  "hd": false,
                  "bm": 0,
                  "c": {
                    "a": 0,
                    "k": [
                      0,
                      0.718,
                      0.8
                    ]
                  },
                  "r": 1,
                  "o": {
                    "a": 0,
                    "k": 100
                  }
                },
                {
                  "ty": "tr",
                  "nm": "Transform",
                  "a": {
                    "a": 0,
                    "k": [
                      123.509,
                      139.927
                    ]
                  },
                  "o": {
                    "a": 0,
                    "k": 100
                  },
                  "p": {
                    "a": 0,
                    "k": [
                      122.969,
                      140.216
                    ]
                  },
                  "r": {
                    "a": 0,
                    "k": 0
                  },
                  "s": {
                    "a": 1,
                    "k": [
                      {
                        "t": 0,
                        "s": [
                          100,
                          100
                        ],
                        "i": {
                          "x": 0.75,
                          "y": 0.75
                        },
                        "o": {
                          "x": 0.25,
                          "y": 0.25
                        }
                      },
                      {
                        "t": 18,
                        "s": [
                          100,
                          100
                        ],
                        "i": {
                          "x": 0.75,
                          "y": 0.75
                        },
                        "o": {
                          "x": 0.25,
                          "y": 0.25
                        }
                      },
                      {
                        "t": 22.5,
                        "s": [
                          0,
                          100
                        ],
                        "i": {
                          "x": 0.75,
                          "y": 0.75
                        },
                        "o": {
                          "x": 0.25,
                          "y": 0.25
                        }
                      },
                      {
                        "t": 27,
                        "s": [
                          100,
                          100
                        ],
                        "i": {
                          "x": 0,
                          "y": 0
                        },
                        "o": {
                          "x": 1,
                          "y": 1
                        }
                      }
                    ]
                  },
                  "sk": {
                    "a": 0,
                    "k": 0
                  },
                  "sa": {
                    "a": 0,
                    "k": 0
                  }
                }
              ],
              "np": 0
            },
            {
              "ty": "gr",
              "hd": false,
              "nm": "Path 1 Group",
              "bm": 0,
              "it": [
                {
                  "ty": "sh",
                  "hd": false,
                  "nm": "Path 1",
                  "d": 1,
                  "ks": {
                    "a": 0,
                    "k": {
                      "c": false,
                      "i": [
                        [
                          0,
                          0
                        ],
                        [
                          0.605,
                          -1.613
                        ],
                        [
                          0,
                          -7.883
                        ],
                        [
                          0.094,
                          -0.207
                        ],
                        [
                          8.106,
                          0
                        ],
                        [
                          0.846,
                          -0.319
                        ],
                        [
                          -3.383,
                          -2.313
                        ],
                        [
                          -8.921,
                          0
                        ],
                        [
                          -0.142,
                          -0.144
                        ],
                        [
                          0,
                          -6.223
                        ],
                        [
                          -1.15,
                          -1.531
                        ],
                        [
                          -0.686,
                          -0.367
                        ],
                        [
                          -1.421,
                          0
                        ],
                        [
                          -0.559,
                          0.303
                        ],
                        [
                          -0.521,
                          1.325
                        ],
                        [
                          -0.066,
                          6.765
                        ],
                        [
                          0,
                          0
                        ],
                        [
                          0,
                          0
                        ],
                        [
                          -0.447,
                          0.176
                        ],
                        [
                          -0.645,
                          1.271
                        ],
                        [
                          -0.016,
                          1.261
                        ],
                        [
                          0.511,
                          0.926
                        ],
                        [
                          0.573,
                          0.429
                        ],
                        [
                          9.238,
                          0
                        ],
                        [
                          0.144,
                          0.144
                        ],
                        [
                          0,
                          5.999
                        ],
                        [
                          1.022,
                          1.499
                        ],
                        [
                          1.964,
                          -0.399
                        ]
                      ],
                      "o": [
                        [
                          -1.722,
                          0.351
                        ],
                        [
                          -0.305,
                          0.828
                        ],
                        [
                          0,
                          5.362
                        ],
                        [
                          -0.16,
                          0.287
                        ],
                        [
                          -8.043,
                          0
                        ],
                        [
                          -3.862,
                          1.437
                        ],
                        [
                          1.501,
                          1.022
                        ],
                        [
                          5.999,
                          0
                        ],
                        [
                          0.144,
                          0.144
                        ],
                        [
                          0,
                          9.24
                        ],
                        [
                          0.431,
                          0.575
                        ],
                        [
                          0.924,
                          0.511
                        ],
                        [
                          1.261,
                          -0.016
                        ],
                        [
                          1.267,
                          -0.649
                        ],
                        [
                          0.178,
                          -0.447
                        ],
                        [
                          0,
                          0
                        ],
                        [
                          0,
                          0
                        ],
                        [
                          6.799,
                          -0.064
                        ],
                        [
                          1.328,
                          -0.517
                        ],
                        [
                          0.303,
                          -0.559
                        ],
                        [
                          0,
                          -1.419
                        ],
                        [
                          -0.367,
                          -0.686
                        ],
                        [
                          -1.533,
                          -1.15
                        ],
                        [
                          -6.224,
                          0
                        ],
                        [
                          -0.144,
                          -0.144
                        ],
                        [
                          0,
                          -8.921
                        ],
                        [
                          -1.134,
                          -1.66
                        ],
                        [
                          0,
                          0
                        ]
                      ],
                      "v": [
                        [
                          52.562,
                          27.127
                        ],
                        [
                          48.671,
                          30.416
                        ],
                        [
                          48.351,
                          39.511
                        ],
                        [
                          48.192,
                          48.048
                        ],
                        [
                          39.654,
                          48.351
                        ],
                        [
                          30.414,
                          48.687
                        ],
                        [
                          29.249,
                          57.829
                        ],
                        [
                          39.974,
                          58.883
                        ],
                        [
                          48.158,
                          59.074
                        ],
                        [
                          48.349,
                          67.532
                        ],
                        [
                          49.483,
                          78.111
                        ],
                        [
                          51.111,
                          79.484
                        ],
                        [
                          53.616,
                          80.027
                        ],
                        [
                          55.803,
                          79.66
                        ],
                        [
                          58.577,
                          76.596
                        ],
                        [
                          58.883,
                          67.5
                        ],
                        [
                          58.963,
                          58.963
                        ],
                        [
                          67.498,
                          58.883
                        ],
                        [
                          76.594,
                          58.579
                        ],
                        [
                          79.658,
                          55.803
                        ],
                        [
                          80.025,
                          53.616
                        ],
                        [
                          79.482,
                          51.111
                        ],
                        [
                          78.111,
                          49.485
                        ],
                        [
                          67.532,
                          48.351
                        ],
                        [
                          59.074,
                          48.16
                        ],
                        [
                          58.883,
                          39.974
                        ],
                        [
                          57.829,
                          29.251
                        ],
                        [
                          52.562,
                          27.127
                        ]
                      ]
                    }
                  }
                },
                {
                  "ty": "fl",
                  "hd": false,
                  "bm": 0,
                  "c": {
                    "a": 0,
                    "k": [
                      0,
                      0.718,
                      0.8
                    ]
                  },
                  "r": 1,
                  "o": {
                    "a": 0,
                    "k": 100
                  }
                },
                {
                  "ty": "tr",
                  "nm": "Transform",
                  "a": {
                    "a": 0,
                    "k": [
                      53.548,
                      53.529
                    ]
                  },
                  "o": {
                    "a": 0,
                    "k": 100
                  },
                  "p": {
                    "a": 0,
                    "k": [
                      53.548,
                      53.529
                    ]
                  },
                  "r": {
                    "a": 1,
                    "k": [
                      {
                        "t": 0,
                        "s": [
                          0
                        ],
                        "i": {
                          "x": 0.75,
                          "y": 0.75
                        },
                        "o": {
                          "x": 0.25,
                          "y": 0.25
                        }
                      },
                      {
                        "t": 6,
                        "s": [
                          180
                        ],
                        "i": {
                          "x": 0,
                          "y": 0
                        },
                        "o": {
                          "x": 1,
                          "y": 1
                        }
                      }
                    ]
                  },
                  "s": {
                    "a": 0,
                    "k": [
                      100,
                      100
                    ]
                  },
                  "sk": {
                    "a": 0,
                    "k": 0
                  },
                  "sa": {
                    "a": 0,
                    "k": 0
                  }
                }
              ],
              "np": 0
            },
            {
              "ty": "gr",
              "hd": false,
              "nm": "Path 1 (3) Group",
              "bm": 0,
              "it": [
                {
                  "ty": "sh",
                  "hd": false,
                  "nm": "Path 1 (3)",
                  "d": 1,
                  "ks": {
                    "a": 0,
                    "k": {
                      "c": false,
                      "i": [
                        [
                          0,
                          0
                        ],
                        [
                          2.411,
                          -0.99
                        ],
                        [
                          2.409,
                          -5.634
                        ],
                        [
                          0.431,
                          -2.265
                        ],
                        [
                          0,
                          -80.488
                        ],
                        [
                          -0.319,
                          -1.674
                        ],
                        [
                          -0.096,
                          -0.16
                        ],
                        [
                          0,
                          -0.158
                        ],
                        [
                          -0.766,
                          -1.309
                        ],
                        [
                          -3.862,
                          -1.884
                        ],
                        [
                          -2.89,
                          -0.655
                        ],
                        [
                          0,
                          0
                        ],
                        [
                          0,
                          0
                        ],
                        [
                          -1.74,
                          1.69
                        ],
                        [
                          0.623,
                          2.01
                        ],
                        [
                          0.86,
                          0.862
                        ],
                        [
                          13.563,
                          0.112
                        ],
                        [
                          2.265,
                          1.054
                        ],
                        [
                          1.243,
                          1.18
                        ],
                        [
                          0.75,
                          1.629
                        ],
                        [
                          -0.048,
                          41.826
                        ],
                        [
                          0,
                          0
                        ],
                        [
                          0,
                          0
                        ],
                        [
                          -0.16,
                          -0.128
                        ],
                        [
                          0,
                          -35.823
                        ],
                        [
                          0.08,
                          -0.064
                        ],
                        [
                          8.857,
                          0
                        ],
                        [
                          1.469,
                          -0.878
                        ],
                        [
                          -0.114,
                          -1.98
                        ],
                        [
                          -0.974,
                          -1.006
                        ],
                        [
                          -1.325,
                          -0.16
                        ],
                        [
                          -32.602,
                          0.032
                        ],
                        [
                          0,
                          0
                        ],
                        [
                          0,
                          0
                        ],
                        [
                          -0.224,
                          0.048
                        ],
                        [
                          -1.626,
                          0.942
                        ],
                        [
                          -1.245,
                          6.863
                        ],
                        [
                          0,
                          71.647
                        ],
                        [
                          0.207,
                          1.165
                        ],
                        [
                          5.155,
                          3.449
                        ],
                        [
                          0.768,
                          0
                        ],
                        [
                          0.196,
                          0.09
                        ],
                        [
                          0.94,
                          0.16
                        ],
                        [
                          10.898,
                          0
                        ],
                        [
                          1.66,
                          -1.611
                        ],
                        [
                          0.287,
                          -0.942
                        ],
                        [
                          -0.399,
                          -1.293
                        ],
                        [
                          -1.054,
                          -0.671
                        ],
                        [
                          -11.633,
                          0
                        ],
                        [
                          -1.102,
                          -0.271
                        ],
                        [
                          -1.74,
                          -1.692
                        ],
                        [
                          -0.734,
                          -1.597
                        ],
                        [
                          0.048,
                          -41.826
                        ],
                        [
                          0,
                          0
                        ],
                        [
                          0,
                          0
                        ],
                        [
                          0.16,
                          0.192
                        ],
                        [
                          -0.016,
                          31.562
                        ],
                        [
                          0,
                          0
                        ],
                        [
                          0,
                          0
                        ],
                        [
                          -1.341,
                          0.671
                        ],
                        [
                          -0.413,
                          0.431
                        ],
                        [
                          3.111,
                          1.613
                        ],
                        [
                          0,
                          0
                        ],
                        [
                          0,
                          0
                        ],
                        [
                          1.341,
                          -0.253
                        ]
                      ],
                      "o": [
                        [
                          -1.82,
                          0.351
                        ],
                        [
                          -5.313,
                          2.201
                        ],
                        [
                          -0.798,
                          1.85
                        ],
                        [
                          -0.319,
                          1.662
                        ],
                        [
                          0,
                          79.977
                        ],
                        [
                          0.16,
                          0.942
                        ],
                        [
                          0.08,
                          0.176
                        ],
                        [
                          0,
                          0.431
                        ],
                        [
                          2.251,
                          3.828
                        ],
                        [
                          2.457,
                          1.181
                        ],
                        [
                          0,
                          0
                        ],
                        [
                          0,
                          0
                        ],
                        [
                          13.531,
                          0.032
                        ],
                        [
                          1.517,
                          -1.485
                        ],
                        [
                          -0.301,
                          -1.006
                        ],
                        [
                          -1.644,
                          -1.642
                        ],
                        [
                          -12.766,
                          -0.111
                        ],
                        [
                          -1.437,
                          -0.669
                        ],
                        [
                          -1.197,
                          -1.149
                        ],
                        [
                          -1.181,
                          -2.568
                        ],
                        [
                          0,
                          0
                        ],
                        [
                          0,
                          0
                        ],
                        [
                          31.532,
                          -0.018
                        ],
                        [
                          0.192,
                          0.16
                        ],
                        [
                          0,
                          26.363
                        ],
                        [
                          -0.08,
                          0.048
                        ],
                        [
                          -17.442,
                          0
                        ],
                        [
                          -1.629,
                          0.942
                        ],
                        [
                          0.08,
                          1.419
                        ],
                        [
                          0.894,
                          0.892
                        ],
                        [
                          0.573,
                          0.064
                        ],
                        [
                          0,
                          0
                        ],
                        [
                          0,
                          0
                        ],
                        [
                          1.004,
                          -0.224
                        ],
                        [
                          0.99,
                          -0.222
                        ],
                        [
                          5.855,
                          -3.383
                        ],
                        [
                          0.207,
                          -1.164
                        ],
                        [
                          0,
                          -71.647
                        ],
                        [
                          -1.15,
                          -6.35
                        ],
                        [
                          -2.01,
                          -1.341
                        ],
                        [
                          -0.216,
                          -0.015
                        ],
                        [
                          -0.16,
                          -0.096
                        ],
                        [
                          -1.597,
                          -0.301
                        ],
                        [
                          -13.483,
                          0
                        ],
                        [
                          -0.846,
                          0.83
                        ],
                        [
                          -0.415,
                          1.357
                        ],
                        [
                          0.351,
                          1.148
                        ],
                        [
                          1.277,
                          0.798
                        ],
                        [
                          9.941,
                          0
                        ],
                        [
                          2.297,
                          0.559
                        ],
                        [
                          1.229,
                          1.165
                        ],
                        [
                          1.179,
                          2.568
                        ],
                        [
                          0,
                          0
                        ],
                        [
                          0,
                          0
                        ],
                        [
                          -35.936,
                          0.032
                        ],
                        [
                          -0.128,
                          -0.16
                        ],
                        [
                          0,
                          0
                        ],
                        [
                          0,
                          0
                        ],
                        [
                          17.376,
                          -0.096
                        ],
                        [
                          0.271,
                          -0.144
                        ],
                        [
                          2.379,
                          -2.537
                        ],
                        [
                          0,
                          0
                        ],
                        [
                          0,
                          0
                        ],
                        [
                          -56.618,
                          -0.016
                        ],
                        [
                          0,
                          0
                        ]
                      ],
                      "v": [
                        [
                          19.069,
                          0.303
                        ],
                        [
                          13.962,
                          1.932
                        ],
                        [
                          1.772,
                          14.283
                        ],
                        [
                          0.319,
                          19.133
                        ],
                        [
                          0,
                          101.97
                        ],
                        [
                          0.319,
                          184.834
                        ],
                        [
                          0.798,
                          186.846
                        ],
                        [
                          0.958,
                          187.451
                        ],
                        [
                          3.127,
                          192.4
                        ],
                        [
                          12.846,
                          201.479
                        ],
                        [
                          18.909,
                          203.568
                        ],
                        [
                          20.665,
                          203.967
                        ],
                        [
                          32.314,
                          203.983
                        ],
                        [
                          46.691,
                          202.421
                        ],
                        [
                          48.03,
                          197.218
                        ],
                        [
                          46.691,
                          195.062
                        ],
                        [
                          32.314,
                          193.404
                        ],
                        [
                          17.935,
                          192.286
                        ],
                        [
                          14.377,
                          189.83
                        ],
                        [
                          11.617,
                          185.904
                        ],
                        [
                          10.563,
                          144.813
                        ],
                        [
                          10.611,
                          107.314
                        ],
                        [
                          53.441,
                          107.268
                        ],
                        [
                          96.477,
                          107.412
                        ],
                        [
                          96.701,
                          150.415
                        ],
                        [
                          96.557,
                          193.324
                        ],
                        [
                          80.312,
                          193.404
                        ],
                        [
                          61.355,
                          194.282
                        ],
                        [
                          58.915,
                          199.022
                        ],
                        [
                          60.397,
                          202.388
                        ],
                        [
                          63.67,
                          203.935
                        ],
                        [
                          123.988,
                          204.015
                        ],
                        [
                          183.268,
                          203.983
                        ],
                        [
                          185.104,
                          203.552
                        ],
                        [
                          187.337,
                          203.041
                        ],
                        [
                          192.396,
                          200.792
                        ],
                        [
                          203.694,
                          184.483
                        ],
                        [
                          203.933,
                          101.97
                        ],
                        [
                          203.694,
                          19.454
                        ],
                        [
                          193.735,
                          3.991
                        ],
                        [
                          187.465,
                          0.958
                        ],
                        [
                          186.842,
                          0.798
                        ],
                        [
                          184.833,
                          0.319
                        ],
                        [
                          171.475,
                          0
                        ],
                        [
                          157.242,
                          1.517
                        ],
                        [
                          155.917,
                          3.576
                        ],
                        [
                          155.901,
                          6.735
                        ],
                        [
                          158.184,
                          9.687
                        ],
                        [
                          171.699,
                          10.533
                        ],
                        [
                          183.667,
                          10.837
                        ],
                        [
                          189.538,
                          14.108
                        ],
                        [
                          192.316,
                          18.033
                        ],
                        [
                          193.368,
                          59.124
                        ],
                        [
                          193.322,
                          96.623
                        ],
                        [
                          150.461,
                          96.669
                        ],
                        [
                          107.408,
                          96.477
                        ],
                        [
                          107.264,
                          53.442
                        ],
                        [
                          107.312,
                          10.613
                        ],
                        [
                          123.988,
                          10.533
                        ],
                        [
                          142.418,
                          9.783
                        ],
                        [
                          143.645,
                          8.745
                        ],
                        [
                          142.179,
                          0.527
                        ],
                        [
                          141.301,
                          0.082
                        ],
                        [
                          80.905,
                          0.05
                        ],
                        [
                          19.071,
                          0.303
                        ]
                      ]
                    }
                  }
                },
                {
                  "ty": "sh",
                  "hd": false,
                  "nm": "Path 1 (3)",
                  "d": 1,
                  "ks": {
                    "a": 0,
                    "k": {
                      "c": true,
                      "i": [
                        [
                          0,
                          0
                        ],
                        [
                          0.128,
                          -0.16
                        ],
                        [
                          35.936,
                          0.032
                        ],
                        [
                          0,
                          0
                        ],
                        [
                          0,
                          0
                        ],
                        [
                          -0.239,
                          1.118
                        ],
                        [
                          -1.793,
                          1.709
                        ],
                        [
                          -2.188,
                          0.556
                        ],
                        [
                          -35.603,
                          -0.016
                        ],
                        [
                          0,
                          0
                        ]
                      ],
                      "o": [
                        [
                          0.016,
                          31.562
                        ],
                        [
                          -0.16,
                          0.192
                        ],
                        [
                          0,
                          0
                        ],
                        [
                          0,
                          0
                        ],
                        [
                          -0.032,
                          -34.865
                        ],
                        [
                          0.56,
                          -2.413
                        ],
                        [
                          1.606,
                          -1.587
                        ],
                        [
                          1.052,
                          -0.253
                        ],
                        [
                          0,
                          0
                        ],
                        [
                          0,
                          0
                        ]
                      ],
                      "v": [
                        [
                          96.669,
                          53.444
                        ],
                        [
                          96.525,
                          96.479
                        ],
                        [
                          53.472,
                          96.671
                        ],
                        [
                          10.611,
                          96.623
                        ],
                        [
                          10.563,
                          59.124
                        ],
                        [
                          10.787,
                          20.428
                        ],
                        [
                          14.393,
                          14.11
                        ],
                        [
                          20.186,
                          10.837
                        ],
                        [
                          58.963,
                          10.583
                        ],
                        [
                          96.621,
                          10.615
                        ]
                      ]
                    }
                  }
                },
                {
                  "ty": "sh",
                  "hd": false,
                  "nm": "Path 1 (3)",
                  "d": 1,
                  "ks": {
                    "a": 0,
                    "k": {
                      "c": true,
                      "i": [
                        [
                          0,
                          0
                        ],
                        [
                          0.239,
                          -1.118
                        ],
                        [
                          4.692,
                          -1.148
                        ],
                        [
                          35.92,
                          0
                        ],
                        [
                          0.08,
                          0.064
                        ],
                        [
                          -0.239,
                          0.238
                        ],
                        [
                          -33.208,
                          -0.018
                        ],
                        [
                          0,
                          0
                        ]
                      ],
                      "o": [
                        [
                          0.032,
                          34.819
                        ],
                        [
                          -1.068,
                          4.658
                        ],
                        [
                          -1.15,
                          0.287
                        ],
                        [
                          -20.615,
                          0
                        ],
                        [
                          -0.24,
                          -0.144
                        ],
                        [
                          0.144,
                          -0.144
                        ],
                        [
                          0,
                          0
                        ],
                        [
                          0,
                          0
                        ]
                      ],
                      "v": [
                        [
                          193.368,
                          144.815
                        ],
                        [
                          193.145,
                          183.511
                        ],
                        [
                          183.667,
                          193.101
                        ],
                        [
                          145.003,
                          193.404
                        ],
                        [
                          107.376,
                          193.308
                        ],
                        [
                          107.424,
                          107.428
                        ],
                        [
                          150.477,
                          107.268
                        ],
                        [
                          193.322,
                          107.314
                        ]
                      ]
                    }
                  }
                },
                {
                  "ty": "fl",
                  "hd": false,
                  "bm": 0,
                  "c": {
                    "a": 0,
                    "k": [
                      0.031,
                      0.275,
                      0.514
                    ]
                  },
                  "r": 1,
                  "o": {
                    "a": 0,
                    "k": 100
                  }
                },
                {
                  "ty": "tr",
                  "nm": "Transform",
                  "a": {
                    "a": 0,
                    "k": [
                      0,
                      0
                    ]
                  },
                  "o": {
                    "a": 0,
                    "k": 100
                  },
                  "p": {
                    "a": 0,
                    "k": [
                      0,
                      0
                    ]
                  },
                  "r": {
                    "a": 0,
                    "k": 0
                  },
                  "s": {
                    "a": 0,
                    "k": [
                      100,
                      100
                    ]
                  },
                  "sk": {
                    "a": 0,
                    "k": 0
                  },
                  "sa": {
                    "a": 0,
                    "k": 0
                  }
                }
              ],
              "np": 0
            }
          ]
        }
      ]
    }
  ],
  "ddd": 0,
  "fr": 30,
  "h": 250,
  "ip": 0,
  "layers": [
    {
      "ddd": 0,
      "ind": 9,
      "ty": 0,
      "nm": "Import from Figma",
      "hd": false,
      "sr": 1,
      "ks": {
        "a": {
          "a": 0,
          "k": [
            51.5,
            51.5
          ]
        },
        "o": {
          "a": 0,
          "k": 100
        },
        "p": {
          "a": 0,
          "k": [
            125,
            125
          ]
        },
        "r": {
          "a": 0,
          "k": 0
        },
        "s": {
          "a": 0,
          "k": [
            100,
            100
          ]
        },
        "sk": {
          "a": 0,
          "k": 0
        },
        "sa": {
          "a": 0,
          "k": 0
        }
      },
      "ao": 0,
      "ip": 0,
      "op": 28,
      "st": 0,
      "bm": 0,
      "h": 103,
      "refId": "el-13-_JY5",
      "w": 103
    },
    {
      "ddd": 0,
      "ind": 10,
      "ty": 4,
      "nm": "Screen",
      "hd": false,
      "sr": 1,
      "ks": {
        "a": {
          "a": 0,
          "k": [
            125,
            125
          ]
        },
        "o": {
          "a": 0,
          "k": 100
        },
        "p": {
          "a": 0,
          "k": [
            125,
            125
          ]
        },
        "r": {
          "a": 0,
          "k": 0
        },
        "s": {
          "a": 0,
          "k": [
            100,
            100
          ]
        },
        "sk": {
          "a": 0,
          "k": 0
        },
        "sa": {
          "a": 0,
          "k": 0
        }
      },
      "ao": 0,
      "ip": 0,
      "op": 28,
      "st": 0,
      "bm": 0,
      "shapes": [
        {
          "ty": "gr",
          "hd": false,
          "nm": "Screen Group",
          "bm": 0,
          "it": [
            {
              "ty": "rc",
              "hd": false,
              "nm": "Screen",
              "d": 1,
              "p": {
                "a": 0,
                "k": [
                  125,
                  125
                ]
              },
              "r": {
                "a": 0,
                "k": 0
              },
              "s": {
                "a": 0,
                "k": [
                  250,
                  250
                ]
              }
            },
            {
              "ty": "fl",
              "hd": false,
              "bm": 0,
              "c": {
                "a": 0,
                "k": [
                  1,
                  1,
                  1
                ]
              },
              "r": 1,
              "o": {
                "a": 0,
                "k": 100
              }
            },
            {
              "ty": "tr",
              "nm": "Transform",
              "a": {
                "a": 0,
                "k": [
                  0,
                  0
                ]
              },
              "o": {
                "a": 0,
                "k": 100
              },
              "p": {
                "a": 0,
                "k": [
                  0,
                  0
                ]
              },
              "r": {
                "a": 0,
                "k": 0
              },
              "s": {
                "a": 0,
                "k": [
                  100,
                  100
                ]
              },
              "sk": {
                "a": 0,
                "k": 0
              },
              "sa": {
                "a": 0,
                "k": 0
              }
            }
          ],
          "np": 0
        }
      ]
    }
  ],
  "meta": {
    "g": "@phase-software/lottie-exporter 0.7.0"
  },
  "nm": "",
  "op": 27,
  "v": "5.6.0",
  "w": 250
}